casdoor/__init__.py
casdoor/adapter.py
casdoor/application.py
casdoor/async_main.py
casdoor/cert.py
casdoor/enforcer.py
casdoor/group.py
casdoor/main.py
casdoor/model.py
casdoor/organization.py
casdoor/payment.py
casdoor/permission.py
casdoor/plan.py
casdoor/pricing.py
casdoor/product.py
casdoor/provider.py
casdoor/resource.py
casdoor/role.py
casdoor/session.py
casdoor/subscription.py
casdoor/syncer.py
casdoor/token.py
casdoor/user.py
casdoor/webhook.py
casdoor-1.40.0.dist-info/licenses/LICENSE
casdoor-1.40.0.dist-info/METADATA
casdoor-1.40.0.dist-info/WHEEL
casdoor-1.40.0.dist-info/top_level.txt
casdoor-1.40.0.dist-info/RECORD
