Metadata-Version: 2.4
Name: casdoor
Version: 1.40.0
Summary: Python SDK built for Casdoor
Home-page: https://github.com/casdoor/casdoor-python-sdk
Author: ffyuanda
Author-email: Casdoor <admin@casdoor.org>
License:                                  Apache License
Project-URL: Home, https://github.com/casdoor/casdoor-python-sdk
Keywords: Casdoor
Platform: any
Classifier: Intended Audience :: Developers
Classifier: License :: OSI Approved :: Apache Software License
Classifier: Operating System :: OS Independent
Classifier: Programming Language :: Python
Classifier: Programming Language :: Python :: 3.6
Classifier: Programming Language :: Python :: 3.7
Classifier: Programming Language :: Python :: 3.8
Classifier: Programming Language :: Python :: 3.9
Classifier: Programming Language :: Python :: 3.10
Classifier: Programming Language :: Python :: 3.11
Classifier: Programming Language :: Python :: 3.12
Requires-Python: >=3.6
License-File: LICENSE
Requires-Dist: aiohttp~=3.10.11
Requires-Dist: cryptography~=44.0.0
Requires-Dist: PyJWT~=2.8.0
Requires-Dist: requests~=2.32.0
Requires-Dist: setuptools>=68.0.0
Requires-Dist: yarl~=1.15.2
Dynamic: license-file
